polars_textproc-0.1.4.dist-info/METADATA
polars_textproc-0.1.4.dist-info/WHEEL
polars_textproc-0.1.4.dist-info/licenses/LICENSE
polars_textproc/__init__.py
polars_textproc/_internal.abi3.so
polars_textproc/_internal.pyi
polars_textproc/typing.py
polars_textproc-0.1.4.dist-info/RECORD
