Metadata-Version: 2.4
Name: polars_textproc
Version: 0.1.4
Classifier: Programming Language :: Rust
Classifier: Programming Language :: Python :: Implementation :: CPython
Classifier: Programming Language :: Python :: Implementation :: PyPy
Requires-Dist: polars>=1.3
License-File: LICENSE
Requires-Python: >=3.9
